[
    {
        "id": 1,
        "category": "Kegiatan Sekolah",
        "title": "Workshop Desain Grafis: Siswa Belajar Teknik Membuat Poster Profesional Menggunakan Canva & Figma",
        "author": "Admin",
        "image": "https://images.unsplash.com/photo-1581091870622-1ee0f9c8d011?q=80&w=1000"
    },
    {
        "id": 2,
        "category": "Lomba",
        "title": "Tim Robotik SMK Meraih Juara Harapan di Kompetisi Nasional Robotika Tahun 2025",
        "author": "Panitia",
        "image": "https://images.unsplash.com/photo-1521791136064-7986c2920216?q=80&w=1000"
    },
    {
        "id": 3,
        "category": "Ekstrakurikuler",
        "title": "Ekskul Pecinta Alam Lakukan Pendakian Gunung Cikuray Sebagai Latihan Dasar Survival",
        "author": "Pembina Ekskul",
        "image": "https://images.unsplash.com/photo-1500530855697-b586d89ba3ee?q=80&w=1000"
    },
    {
        "id": 4,
        "category": "Pengumuman",
        "title": "Libur Semester Dimulai 20 Desember 2025 – Cek Jadwalnya!",
        "author": "Admin",
        "image": "https://images.unsplash.com/photo-1524995997946-a1c2e315a42f?q=80&w=1000"
    }
]